{
  "name": "Recipe AI Generator",
  "build": {
    "dockerfile": "Dockerfile",
    "context": ".."
  },
  "features": {
    "ghcr.io/devcontainers/features/python:1": {
      "version": "3.11"
    },
    "ghcr.io/devcontainers/features/git:1": {},
    "ghcr.io/devcontainers/features/github-cli:1": {}
  },
  "customizations": {
    "vscode": {
      "extensions": [
        "ms-python.python",
        "ms-python.vscode-pylance",
        "ms-python.debugpy",
        "ms-python.black-formatter",
        "ms-python.isort",
        "ms-python.flake8",
        "ms-toolsai.jupyter",
        "esbenp.prettier-vscode",
        "dbaeumer.vscode-eslint",
        "formulahendry.auto-rename-tag",
        "christian-kohler.path-intellisense",
        "streetsidesoftware.code-spell-checker"
      ],
      "settings": {
        "python.defaultInterpreterPath": "/usr/local/bin/python",
        "python.linting.enabled": true,
        "python.linting.pylintEnabled": true,
        "python.formatting.provider": "black",
        "python.formatting.blackPath": "/usr/local/bin/black",
        "python.terminal.activateEnvironment": true,
        "editor.formatOnSave": true,
        "editor.codeActionsOnSave": {
          "source.organizeImports": true
        },
        "terminal.integrated.defaultProfile.linux": "bash"
      }
    }
  },
  "postCreateCommand": "echo 'Environment ready!'",
  "postStartCommand": "echo 'Welcome to Recipe AI Generator! Run \"flask run\" to start the application.'",
  "forwardPorts": [8000],
  "portsAttributes": {
    "8000": {
      "label": "Flask App",
      "onAutoForward": "notify"
    }
  },
  "remoteUser": "vscode",
  "mounts": [
    "source=${localWorkspaceFolder},target=/workspace,type=bind,consistency=cached"
  ],
  "workspaceFolder": "/workspace",
  "env": {
    "FLASK_APP": "app.py",
    "FLASK_ENV": "development",
    "FLASK_DEBUG": "1"
  }
}